<?xml version="1.0" encoding="UTF-8"?>
<persistence version="2.2" xmlns="http://xmlns.jcp.org/xml/ns/persistence" xmlns:xsi="http://www.w3.org/2001/XMLSchema-instance" xsi:schemaLocation="http://xmlns.jcp.org/xml/ns/persistence           http://xmlns.jcp.org/xml/ns/persistence/persistence_2_2.xsd">
  <persistence-unit name="com.mycompany_Programation2_Project2_MMontiel_jar_1.0-SNAPSHOTPU" transaction-type="RESOURCE_LOCAL">
    <provider>org.eclipse.persistence.jpa.PersistenceProvider</provider>
    <class>com.mycompany.programation2_project2_mmontiel.DataBase.Project2TotalPayComissions</class>
    <class>com.mycompany.programation2_project2_mmontiel.DataBase.Project2Rooms</class>
    <class>com.mycompany.programation2_project2_mmontiel.DataBase.Project2ComissionRegister</class>
    <class>com.mycompany.programation2_project2_mmontiel.DataBase.Project2Collections</class>
    <class>com.mycompany.programation2_project2_mmontiel.DataBase.Project2RoomValoration</class>
    <class>com.mycompany.programation2_project2_mmontiel.DataBase.Project2ChipsRooms</class>
    <class>com.mycompany.programation2_project2_mmontiel.DataBase.Project2Prices</class>
    <class>com.mycompany.programation2_project2_mmontiel.DataBase.Project2Museum</class>
    <class>com.mycompany.programation2_project2_mmontiel.DataBase.Project2ComissionsKey</class>
    <class>com.mycompany.programation2_project2_mmontiel.DataBase.Project2Species</class>
    <class>com.mycompany.programation2_project2_mmontiel.DataBase.Project2AutoriceEntrance</class>
    <class>com.mycompany.programation2_project2_mmontiel.DataBase.Project2Entrance</class>
    <class>com.mycompany.programation2_project2_mmontiel.DataBase.Project2Themes</class>
    <properties>
      <property name="javax.persistence.jdbc.url" value="jdbc:oracle:thin:@192.168.192.189:1521:XE"/>
      <property name="javax.persistence.jdbc.user" value="MMONTIELV"/>
      <property name="javax.persistence.jdbc.driver" value="oracle.jdbc.OracleDriver"/>
      <property name="javax.persistence.jdbc.password" value="una2025"/>
    </properties>
  </persistence-unit>
</persistence>
